<?xml version="1.0" encoding="UTF-8"?>
<objects serializationModel="Studio.02.03.00">
	<object class="ParameterPreset" id="{f844f4e0-6612-420d-a779-223e9400f576}">
		<property name="name">
			<value>FM</value>
		</property>
		<relationship name="folder">
			<destination>{ce6d2344-96c9-42ee-9081-b58ed7aadc13}</destination>
		</relationship>
		<relationship name="parameter">
			<destination>{79f52d5f-598d-4c51-9e38-7b2cd971e3f5}</destination>
		</relationship>
	</object>
	<object class="GameParameter" id="{79f52d5f-598d-4c51-9e38-7b2cd971e3f5}">
		<property name="initialValue">
			<value>0</value>
		</property>
	</object>
</objects>
